tccgs/__init__.py
tccgs/__main__.py
tccgs/config.py
tccgs/logger.py
tccgs/logger_config.toml
tccgs/py.typed
tccgs/script.py
tccgs/data/icon_ico.ico
tccgs/data/thanks_button.png
tccgs/data/tsukasa.gif
tsukasa_credit_card_gag_scam-1.2.0.dist-info/METADATA
tsukasa_credit_card_gag_scam-1.2.0.dist-info/WHEEL
tsukasa_credit_card_gag_scam-1.2.0.dist-info/entry_points.txt
tsukasa_credit_card_gag_scam-1.2.0.dist-info/RECORD
