Metadata-Version: 2.4
Name: tsukasa-credit-card-gag-scam
Version: 1.2.0
Summary: A joke program based on a popular credit card scam meme
Project-URL: Original source code, https://github.com/Bleeplo/Tsukasa-credit-card-gag-scam
Project-URL: Original Windows executable, https://drive.google.com/file/d/1gVKI089Y7Ub7MrqNmRwsvOGZYS3msnIu/view?usp=sharing
Project-URL: Updated source code, https://github.com/Diapolo10/Tsukasa-credit-card-gag-scam
Project-URL: Updated executables, https://github.com/Diapolo10/Tsukasa-credit-card-gag-scam/releases
Project-URL: Documentation, https://github.com/Diapolo10/iplib3/tree/main/docs
Author-email: Bleeplo <bleeplo@users.noreply.github.com>
Maintainer-email: Lari Liuhamo <lari.liuhamo+github@gmail.com>
License-Expression: MIT
Requires-Python: >=3.11.0
Requires-Dist: pillow>=11.2.1
Requires-Dist: python-dotenv>=1.1.0
